overprivileged/__init__.py
overprivileged/cli.py
overprivileged/clients.py
overprivileged/cloudwatch.py
overprivileged/iam/__init__.py
overprivileged/iam/action.py
overprivileged/iam/policy.py
overprivileged/iam/role.py
overprivileged/static/__init__.py
overprivileged/static/iam_actions.py
overprivileged-0.0.1.dist-info/LICENSE
overprivileged-0.0.1.dist-info/METADATA
overprivileged-0.0.1.dist-info/WHEEL
overprivileged-0.0.1.dist-info/entry_points.txt
overprivileged-0.0.1.dist-info/top_level.txt
overprivileged-0.0.1.dist-info/RECORD
