Metadata-Version: 2.1
Name: overprivileged
Version: 0.0.1
Summary: CLI for discovering overprivileged AWS IAM roles
Home-page: https://github.com/nplutt/overprivileged
Author: Nick Plutt
Author-email: nplutt@gmail.com
License: MIT
Project-URL: Source Code, https://github.com/nplutt/overprivileged/
Keywords: overprivileged aws iam cloudtrail roles python
Platform: UNKNOWN
Classifier: Intended Audience :: Developers
Classifier: Programming Language :: Python :: 3.6
Classifier: Programming Language :: Python :: 3.7
Classifier: Programming Language :: Python :: 3.8
Requires-Python: >=3.6
Requires-Dist: boto3
Requires-Dist: click
Provides-Extra: dev
Requires-Dist: black ; extra == 'dev'
Requires-Dist: isort ; extra == 'dev'
Requires-Dist: requests ; extra == 'dev'
Provides-Extra: test
Requires-Dist: pytest ; extra == 'test'
Requires-Dist: pytest-cov ; extra == 'test'
